{
  "version": "1.0",
  "generated": "2026-05-02",
  "files": [
    {
      "id": "edu001_exported_doc",
      "filename": "exported_doc.pdf",
      "title": "exported_doc",
      "type": "pdf",
      "htmlContent": "<p>📄 點擊下方按鈕開啟 PDF 文件：<br><a href=\"https://raw.githubusercontent.com/dreamcheap2000/Clinical-Medicine/main/Patient%20education/exported_doc.pdf\" target=\"_blank\" rel=\"noopener\" style=\"display:inline-block;margin-top:8px;padding:8px 16px;background:#1a73e8;color:#fff;border-radius:6px;text-decoration:none\">🔗 開啟 exported_doc.pdf</a></p>",
      "images": [],
      "pdfUrl": "https://raw.githubusercontent.com/dreamcheap2000/Clinical-Medicine/main/Patient%20education/exported_doc.pdf"
    },
    {
      "id": "edu002________",
      "filename": "無痛關節鬆動術.docx",
      "title": "無痛關節鬆動術",
      "type": "docx",
      "htmlContent": "<p><strong>解鎖冰封的肩膀：無痛肩關節鬆動術 (Silent Manipulation)</strong></p><p>「Silent Manipulation」是一種強調<strong>優雅且精準</strong>的技術。與傳統需全身麻醉的激烈治療不同，此技術源自日本，著重於<strong>細膩的手法</strong>與<strong>受控的力道</strong>，能在您完全清醒且無痛的狀態下，安靜且有節奏地解開關節沾黏。</p><p>一、 適合的對象（適應症）</p><p>若您的肩膀符合以下情況，此技術能提供幫助：</p><ul><li><strong>活動極度受限</strong>：手向前舉不超過 100°、手無法向外旋轉，或「手摸背」高度低於腰部以下。</li><li><strong>保守治療無效</strong>：經過 3 到 6 個月的藥物、打針或物理治療，進步仍不明顯。</li><li><strong>嚴重影響生活</strong>：疼痛導致失眠，或因肩膀僵硬而無法穿衣、梳頭與工作。</li></ul><p>二、 療程三階段與注意事項</p><p>1. 治療前：準備與禁忌</p><ul><li><strong>著裝</strong>：穿著方便露出肩膀的衣物。</li><li><strong>交通</strong>：<strong>嚴禁自駕</strong>。治療後手臂會暫時麻痺 12 小時，請務必安排親友接送或搭乘計程車。</li><li><strong>禁忌症</strong>：如有急性骨折、關節感染、嚴重骨質疏鬆或單側肺部手術史者，需主動告知醫師評估。</li></ul><p>2. 治療中：舒適的體驗</p><p>在全程清醒且無痛的狀態下，醫師將執行以下三個步驟：</p><ol><li><strong>超音波導引神經阻斷</strong>：透過超音波導引，精準阻斷頸部神經傳導，使肩膀處於無痛狀態。</li><li><strong>肩關節類固醇注射</strong>：注射些許類固醇至前肩關節、喙肱韌帶與三角肌下滑囊，以減少治療後的發炎性疼痛。</li><li><strong>鬆動術（精準鬆動）</strong>：在確保安全與穩定的前提下，系統化地鬆開沾黏的關節囊。在鬆動術的過程中，您可能會聽到或感覺到「啵」、「喀啦」或「撕裂」的聲響與感覺，這是因為緊縮的關節囊結構正在被鬆解。這些聲響和感覺是預期的，並代表關節囊已成功鬆開。</li></ol><p>3. 治療後：黃金康復期</p><ul><li><strong>三角巾固定</strong>：治療後會使用三角巾固定，隔天麻醉消退後即可移除。</li><li><strong>即刻活動</strong>：移除三角巾後，需開始正常生活使用，並積極配合復健運動。</li><li><strong>持續復健</strong>：術後 <strong>8 週內</strong>是防止再次沾黏的黃金期，需喚醒因長期停用而萎縮的肌肉。</li></ul><p><strong>三、 臨床數據：安全性與療效</strong></p><p>根據大型臨床研究的追蹤數據顯示，「無痛肩關節鬆動術」具有高度的安全性和顯著的療效。</p><p><strong>關節活動度改善：治療 3 個月後的平均角度變化</strong></p><table><thead><tr><th><p><strong>關節活動度</strong></p></th><th><p><strong>治療前 (平均)</strong></p></th><th><p><strong>治療後 3 個月 (平均)</strong></p></th><th><p><strong>改善說明</strong></p></th></tr><tr><th><p><strong>手向前抬高</strong></p></th><th><p>98.8°</p></th><th><p>155.5°</p></th><th><p>顯著恢復</p></th></tr><tr><th><p><strong>手向側抬高</strong></p></th><th><p>75.6°</p></th><th><p>152.9°</p></th><th><p>角度翻倍</p></th></tr><tr><th><p><strong>手向外旋轉</strong></p></th><th><p>2.7°</p></th><th><p>45.9°</p></th><th><p>改善幅度最大</p></th></tr></thead></table><p><strong>安全性與風險</strong></p><ul><li><strong>極低副作用</strong>：在 1,665 例追蹤中，<strong>無任何</strong>骨折或脫位等嚴重併發症發生。</li><li><strong>復發機率</strong>：僅約 <strong>7%</strong> 的患者可能因體質或復健不足需再次做鬆動術。</li></ul>",
      "images": []
    }
  ]
}